data/__init__.py
data/admin.py
data/apps.py
data/models.py
data/tests.py
data/urls.py
data/views.py
data/management/commands/analytics_api.py
data/management/commands/updates.py
data/migrations/__init__.py
data/static/data/css/data-style.css
data/templates/data/index.html
zfl_data-0.0.5.dist-info/METADATA
zfl_data-0.0.5.dist-info/WHEEL
zfl_data-0.0.5.dist-info/licenses/LICENSE.txt
zfl_data-0.0.5.dist-info/RECORD
